mirascope_cli/__init__.py
mirascope_cli/commands/__init__.py
mirascope_cli/commands/add.py
mirascope_cli/commands/init.py
mirascope_cli/commands/py.typed
mirascope_cli/commands/remove.py
mirascope_cli/commands/status.py
mirascope_cli/commands/use.py
mirascope_cli/constants.py
mirascope_cli/enums.py
mirascope_cli/generic/__init__.py
mirascope_cli/generic/mirascope.ini.j2
mirascope_cli/generic/prompt_template.j2
mirascope_cli/main.py
mirascope_cli/py.typed
mirascope_cli/schemas.py
mirascope_cli/utils.py
mirascope_cli-0.1.3.dist-info/LICENSE
mirascope_cli-0.1.3.dist-info/METADATA
mirascope_cli-0.1.3.dist-info/WHEEL
mirascope_cli-0.1.3.dist-info/entry_points.txt
mirascope_cli-0.1.3.dist-info/RECORD
