Metadata-Version: 2.1
Name: mirascope-cli
Version: 0.1.3
Summary: The Mirascope Command Line Interface
Home-page: https://github.com/Mirascope/mirascope-cli
License: MIT
Author: William Bakst
Author-email: william@mirascope.io
Requires-Python: >=3.9,<4.0
Classifier: License :: OSI Approved :: MIT License
Classifier: Programming Language :: Python :: 3
Classifier: Programming Language :: Python :: 3.9
Classifier: Programming Language :: Python :: 3.10
Classifier: Programming Language :: Python :: 3.11
Classifier: Programming Language :: Python :: 3.12
Requires-Dist: Jinja2 (>=3.1.4,<4.0.0)
Requires-Dist: pydantic (>=2.0.2,<3.0.0)
Requires-Dist: typer[all] (>=0.9.0,<1.0.0)
Project-URL: Repository, https://github.com/Mirascope/mirascope-cli
